[
  {
    "slug": "about-me",
    "date": "2026-07-19",
    "cover": "img/picture.png",
    "tags": ["about", "hallo"],
    "title": {
      "de": "Hallo, ich bin Pascal",
      "en": "Hi, I'm Pascal"
    },
    "excerpt": {
      "de": "Systems Engineer, Python-Veteran und IT-Berater aus Augsburg — wer ich bin, was ich mache und wie du mich erreichst.",
      "en": "Systems engineer, Python veteran and IT consultant from Augsburg — who I am, what I do, and how to reach me."
    }
  },
  {
    "slug": "first-post",
    "date": "2026-06-13",
    "cover": "img/REST.png",
    "tags": ["meta", "blog"],
    "title": {
      "de": "Willkommen auf meinem Blog",
      "en": "Welcome to my blog"
    },
    "excerpt": {
      "de": "Hier teile ich meine Projekte, Gedanken zur Softwareentwicklung und ein paar coole Fotos.",
      "en": "Here I share my projects, thoughts on software development, and a few cool photos."
    }
  }
]
